.hgignore
.hgtags
CHANGES.rst
LICENSE.txt
MANIFEST.in
README.rst
bootstrap.py
buildout.cfg
setup.py
js/__init__.py
js.chosen.egg-info/PKG-INFO
js.chosen.egg-info/SOURCES.txt
js.chosen.egg-info/dependency_links.txt
js.chosen.egg-info/entry_points.txt
js.chosen.egg-info/namespace_packages.txt
js.chosen.egg-info/not-zip-safe
js.chosen.egg-info/requires.txt
js.chosen.egg-info/top_level.txt
js/chosen/__init__.py
js/chosen/test_chosen.txt
js/chosen/resources/chosen-sprite.png
js/chosen/resources/chosen-sprite@2x.png
js/chosen/resources/chosen.css
js/chosen/resources/chosen.jquery.js
js/chosen/resources/chosen.jquery.min.js
js/chosen/resources/chosen.min.css
js/chosen/resources/chosen.proto.js
js/chosen/resources/chosen.proto.min.js