Metadata-Version: 1.0
Name: js.chosen
Version: 1.8.7
Summary: Fanstatic packaging of Chosen
Home-page: UNKNOWN
Author: Fanstatic Developers
Author-email: fanstatic@googlegroups.com
License: BSD
Platform: UNKNOWN
